{
    "user_id": "skill_cluster_web_development_2",
    "preferred_field": "Technology",
    "preferred_specialization": "Software Development",
    "current_skills": [
        "Debugging",
        "Version Control",
        "Data Structures",
        "System Architecture",
        "Database Management",
        "API Design",
        "Unit Testing",
        "Programming",
        "Software Testing"
    ],
    "lacking_skills": [
        "Web Development",
        "Problem Solving",
        "Algorithms"
    ],
    "timestamp": "2025-04-10T14:10:45.749193"
}