{
    "user_id": "skill_cluster_communication_skills_1",
    "preferred_field": "Education",
    "preferred_specialization": "Elementary Education",
    "current_skills": [
        "Classroom Management",
        "Instructional Strategies",
        "Mathematics Instruction",
        "Child Development",
        "Literacy Instruction",
        "Special Education Awareness",
        "Educational Technology"
    ],
    "lacking_skills": [
        "Communication Skills",
        "Behavior Management",
        "Differentiated Instruction",
        "Assessment Methods",
        "Curriculum Development"
    ],
    "timestamp": "2025-04-10T14:10:45.701152"
}