{
    "user_id": "user4",
    "preferred_field": "Technology",
    "preferred_specialization": "Cybersecurity",
    "current_skills": [
        "Network Security",
        "Information Security",
        "Ethical Hacking",
        "Risk Management",
        "Incident Response",
        "Security Tools",
        "Cloud Security"
    ],
    "lacking_skills": [
        "Cryptography",
        "Digital Forensics",
        "Penetration Testing",
        "Security Auditing",
        "Malware Analysis"
    ],
    "timestamp": "2025-04-09T20:49:31.736668"
}